<?xml version="1.0" encoding="UTF-8" ?>
<!DOCTYPE generatorConfiguration PUBLIC "-//mybatis.org//DTD MyBatis Generator Configuration 1.0//EN"
        "http://mybatis.org/dtd/mybatis-generator-config_1_0.dtd" >
<generatorConfiguration>
<!--     <classPathEntry location="/Users/jeng/.m2/repository/mysql/mysql-connector-java/5.1.31/mysql-connector-java-5.1.31.jar" /> -->
    <classPathEntry location="E:\work\repository\mysql\mysql-connector-java\5.1.31\mysql-connector-java-5.1.31.jar" />

    <context id="context1"
             targetRuntime="com.xmomen.maven.plugins.mybatis.generator.context.IntrospectedTableMyBatis3ImplExt">

        <plugin type="com.xmomen.maven.plugins.mybatis.generator.plugins.ModelAnnotationPlugin" />
        <plugin type="com.xmomen.maven.plugins.mybatis.generator.plugins.MapperGeneratorPlugin">
            <property name="rootInterface" value="com.xmomen.framework.mybatis.mapper.MybatisMapper"/>
        </plugin>
        <plugin type="com.xmomen.maven.plugins.mybatis.generator.plugins.ModelExamplePlugin" >
            <property name="rootClass" value="com.xmomen.framework.mybatis.model.BaseMybatisExample" />
        </plugin>
        <plugin type="com.xmomen.maven.plugins.mybatis.generator.plugins.MapperSqlMapGeneratorPlugin" />
        <plugin type="com.xmomen.maven.plugins.mybatis.generator.plugins.PrimaryKeyGeneratorPlugin" />
        <commentGenerator>
            <property name="suppressAllComments" value="true" />
            <property name="suppressDate" value="true" />
        </commentGenerator>

        <jdbcConnection driverClass="com.mysql.jdbc.Driver"
                        connectionURL="jdbc:mysql://120.24.236.186:3306/dms_dev?useUnicode=true&amp;characterEncoding=UTF-8"
                        userId="dms_dev" password="dev" />

        <javaTypeResolver type="com.xmomen.maven.plugins.mybatis.generator.plugins.types.JavaTypeResolverDefaultImplExt"></javaTypeResolver>

        <javaModelGenerator targetPackage="com.xmomen.module.base.entity"
                            targetProject="./src/main/java" >
            <property name="rootClass" value="com.xmomen.framework.mybatis.model.BaseMybatisModel" />
        </javaModelGenerator>

        <sqlMapGenerator targetPackage="com.xmomen.module.base.entity.mapper"
                         targetProject="./src/main/resources" />
        <javaClientGenerator targetPackage="com.xmomen.module.base.entity.mapper"
                             targetProject="./src/main/java" type="XMLMAPPER" >
        </javaClientGenerator>
        <!--    用户模块    -->
        <table tableName="cd_category" />
		<table tableName="cd_company"/>
		<table tableName="cd_contract"/>
		<table tableName="cd_coupon"/>
		<table tableName="cd_coupon_ref"/>
		<table tableName="cd_item"/>
		<table tableName="cd_item_contract_item"/>
		<table tableName="cd_item_ref"/>
		<table tableName="cd_manager_company"/>
		<table tableName="cd_member"/>
    </context>
</generatorConfiguration>